flexy_token/__init__.py
flexy_token/api_client.py
flexy_token/get_url.py
flexydial_token-0.12.dist-info/LICENSE
flexydial_token-0.12.dist-info/METADATA
flexydial_token-0.12.dist-info/WHEEL
flexydial_token-0.12.dist-info/top_level.txt
flexydial_token-0.12.dist-info/RECORD
